curve_linear/__init__.py
curve_linear/logic/__init__.py
curve_linear/logic/feature_transformer.py
curve_linear/logic/model.py
curve_linear-0.0.1.dist-info/METADATA
curve_linear-0.0.1.dist-info/WHEEL
curve_linear-0.0.1.dist-info/top_level.txt
curve_linear-0.0.1.dist-info/RECORD
