Metadata-Version: 2.1
Name: curve-linear
Version: 0.0.1
Summary: Linear model of monotonic curves of each feature
Home-page: https://github.com/not-so-fat/curve_linear
Author: @not-so-fat
Author-email: conjurer.not.so.fat@gmail.com
License: UNKNOWN
Platform: UNKNOWN
Classifier: Programming Language :: Python :: 3
Classifier: License :: OSI Approved :: MIT License
Classifier: Operating System :: OS Independent
Requires-Python: >=3.6
Requires-Dist: lightgbm (==3.2.1)
Requires-Dist: scikit-learn (==0.24.1)
Requires-Dist: pandas (==1.2.4)
Requires-Dist: numpy (==1.20.0)
